fillfdb/__init__.py
fillfdb/fillfdb.py
fillfdb-0.1.0.dist-info/WHEEL
fillfdb-0.1.0.dist-info/METADATA
fillfdb-0.1.0.dist-info/RECORD
